ereader/__init__.py
ereader/__main__.py
ereader-0.1.0.dist-info/LICENSE
ereader-0.1.0.dist-info/METADATA
ereader-0.1.0.dist-info/WHEEL
ereader-0.1.0.dist-info/entry_points.txt
ereader-0.1.0.dist-info/top_level.txt
ereader-0.1.0.dist-info/RECORD
