Metadata-Version: 2.1
Name: ereader
Version: 0.1.0
Summary: GCP Error Reporting reading tool
Home-page: UNKNOWN
Author: Himaster
Author-email: himaster@inbox.ru
License: UNKNOWN
Platform: UNKNOWN
Requires-Python: ==2.7.*
Requires-Dist: cachetools (==3.1.1)
Requires-Dist: certifi (==2021.5.30)
Requires-Dist: chardet (==4.0.0)
Requires-Dist: enum34 (==1.1.10)
Requires-Dist: futures (==3.3.0)
Requires-Dist: google-api-core (==1.29.0)
Requires-Dist: google-auth (==1.30.1)
Requires-Dist: google-cloud-core (==1.6.0)
Requires-Dist: google-cloud-error-reporting (==0.34.0)
Requires-Dist: google-cloud-logging (==1.15.1)
Requires-Dist: googleapis-common-protos (==1.52.0)
Requires-Dist: grpcio (==1.38.0)
Requires-Dist: idna (==2.10)
Requires-Dist: packaging (==20.9)
Requires-Dist: protobuf (==3.17.2)
Requires-Dist: pyasn1 (==0.4.8)
Requires-Dist: pyasn1-modules (==0.2.8)
Requires-Dist: pyparsing (==2.4.7)
Requires-Dist: pytz (==2021.1)
Requires-Dist: requests (==2.25.1)
Requires-Dist: rsa (==4.5)
Requires-Dist: six (==1.16.0)
Requires-Dist: urllib3 (==1.26.5)
